Memórias/ROM Simples/rom.vhd
--------------------------------------------------
--!  Gustavo Trivelatto Gabriel
--!  NUSP: 11260908
--------------------------------------------------

library ieee;
use ieee.numeric_std.all;

entity rom_simples is
  port (
    addr : in  bit_vector(3 downto 0);
	data : out bit_vector(7 downto 0)
  );
end rom_simples;

architecture arch of rom_simples is
  type mem_tipo is array (0 to 15) of bit_vector(7 downto 0);
  constant mem: mem_tipo :=
   (0  => "00000000",
    1  => "00000011",
	2  => "11000000",
	3  => "00001100",
	4  => "00110000",
    5  => "01010101",
	6  => "10101010",
	7  => "11111111",
	8  => "11100000",
    9  => "11100111",
	10 => "00000111",
	11 => "00011000",
	12 => "11000011",
    13 => "00111100",
	14 => "11110000",
	15 => "00001111");

function TO_INTEGER (ARG: bit_vector) return NATURAL is
  constant ARG_LEFT: INTEGER := ARG'LENGTH-1;
  alias XARG: bit_vector(ARG_LEFT downto 0) is ARG;
  variable RESULT: NATURAL := 0;
begin
  for I in XARG'RANGE loop
    RESULT := RESULT+RESULT;
    if XARG(I) = '1' then
      RESULT := RESULT + 1;
    end if;
  end loop;
  return RESULT;
end TO_INTEGER;

begin
  data <= mem(TO_INTEGER(addr));
end arch;

Memórias/ROM Simples/rom_tb.vhd
-------------------------------------------------------
--! Gustavo Trivelatto Gabriel
--! NUSP: 11260908
-------------------------------------------------------

library ieee;
use ieee.std_logic_1164.all;
use ieee.numeric_std.all;

entity rom_tb is
end entity;

architecture tb of rom_tb is
  
  component rom_simples
    port (
      addr : in  bit_vector(3 downto 0);
	  data : out bit_vector(7 downto 0)
    );
  end component;
  
  signal addr_in: bit_vector(3 downto 0);
  signal data_out: bit_vector(7 downto 0);
  
begin
  dut: rom_simples
       port map(addr=>   addr_in,
                data=>   data_out
      );

  stimulus: process is
	
	type pattern_type is record
		address: bit_vector(3 downto 0);
		dados:   bit_vector(7 downto 0);
	end record;
	
	type pattern_array is array (natural range <>) of pattern_type;
	
	constant patterns: pattern_array :=
		
		(("0000","00000000"),
		 ("0001","00000011"),
		 ("0010","11000000"),
		 ("0011","00001100"),
		 ("0100","00110000"),
		 ("0101","01010101"),
		 ("0110","10101010"),
		 ("0111","11111111"),
		 ("1000","11100000"),
		 ("1001","11100111"),
		 ("1010","00000111"),
		 ("1011","00011000"),
		 ("1100","11000011"),
		 ("1101","00111100"),
		 ("1110","11110000"),
		 ("1111","00001111"));
		 
  
  begin
  
    assert false report "simulation start" severity note;
    
    for i in patterns'range loop
         addr_in <= patterns(i).address;
         
         wait for 10 ns;
         
         assert data_out = patterns(i).dados report "Dado nao confere" severity error;
        
      end loop;
 
    -- final do testbench
    assert false report "simulation end" severity note;
    
    wait; -- fim da simulação: aguarda indefinidamente
  end process;


end architecture;

Memórias/ROM Simples/rom_tb.vcd
$date
  Tue Sep 22 17:56:36 2020
$end
$version
  GHDL v0
$end
$timescale
  1 fs
$end
$scope module standard $end
$upscope $end
$scope module std_logic_1164 $end
$upscope $end
$scope module numeric_std $end
$upscope $end
$scope module rom_tb $end
$var reg 4 ! addr_in[3:0] $end
$var reg 8 " data_out[7:0] $end
$scope module dut $end
$var reg 4 # addr[3:0] $end
$var reg 8 $ data[7:0] $end
$upscope $end
$upscope $end
$enddefinitions $end
#0
b0000 !
b00000000 "
b0000 #
b00000000 $
#10000000
b0001 !
b00000011 "
b0001 #
b00000011 $
#20000000
b0010 !
b11000000 "
b0010 #
b11000000 $
#30000000
b0011 !
b00001100 "
b0011 #
b00001100 $
#40000000
b0100 !
b00110000 "
b0100 #
b00110000 $
#50000000
b0101 !
b01010101 "
b0101 #
b01010101 $
#60000000
b0110 !
b10101010 "
b0110 #
b10101010 $
#70000000
b0111 !
b11111111 "
b0111 #
b11111111 $
#80000000
b1000 !
b11100000 "
b1000 #
b11100000 $
#90000000
b1001 !
b11100111 "
b1001 #
b11100111 $
#100000000
b1010 !
b00000111 "
b1010 #
b00000111 $
#110000000
b1011 !
b00011000 "
b1011 #
b00011000 $
#120000000
b1100 !
b11000011 "
b1100 #
b11000011 $
#130000000
b1101 !
b00111100 "
b1101 #
b00111100 $
#140000000
b1110 !
b11110000 "
b1110 #
b11110000 $
#150000000
b1111 !
b00001111 "
b1111 #
b00001111 $
