Memórias/RAM/ram.vhd
--------------------------------------------------
--!  Gustavo Trivelatto Gabriel
--!  NUSP: 11260908
--------------------------------------------------

library ieee;
use ieee.numeric_std.all;

entity ram is 
  generic (
    addressSize : natural := 4;
	wordSize    : natural := 8
  );
  port (
    ck, wr : in  bit;
	addr   : in  bit_vector(addressSize-1 downto 0);
	data_i : in  bit_vector(wordSize-1 downto 0);
	data_o : out bit_vector(wordSize-1 downto 0)
  );
end ram;

architecture arch of ram is
  type mem_tipo is array (0 to (2**addressSize)-1) of bit_vector(wordSize-1 downto 0);
  signal mem: mem_tipo;

function TO_INTEGER (ARG: bit_vector) return NATURAL is
  constant ARG_LEFT: INTEGER := ARG'LENGTH-1;
  alias XARG: bit_vector(ARG_LEFT downto 0) is ARG;
  variable RESULT: NATURAL := 0;
begin
  for I in XARG'RANGE loop
    RESULT := RESULT+RESULT;
    if XARG(I) = '1' then
      RESULT := RESULT + 1;
    end if;
  end loop;
  return RESULT;
end TO_INTEGER;

begin 
  wrt: process(ck)
  begin
	if (ck='1' and ck'event) then
	  if (wr='1') then
	    mem(TO_INTEGER(addr)) <= data_i;
	  end if;
	end if;
  end process;
  
  data_o <= mem(TO_INTEGER(addr));
		


end arch;

Memórias/RAM/ram_sincrona_tb.vhd
library ieee;
use ieee.std_logic_1164.ALL;
use ieee.numeric_std.ALL;

entity ram_tb is
end ram_tb;

architecture tb_ram of ram_tb is
    component ram
        generic (
            addressSize: natural := 4;
            wordSize: natural := 8
        );
        port (
            ck, wr: in bit;
            addr: in bit_vector(addressSize-1 downto 0); 
            data_i: in bit_vector(wordSize-1 downto 0);
            data_o: out bit_vector(wordSize-1 downto 0)
        );
    end component ram;

    signal ck3_tb, ck4_tb, wr3_tb, wr4_tb: bit;
    signal addr_tb_4bits: bit_vector (3 downto 0);
    signal datai_tb_4bits, datao_tb_4bits: bit_vector (7 downto 0);
    signal addr_tb_3bits: bit_vector (2 downto 0);
    signal datai_tb_3bits, datao_tb_3bits: bit_vector (3 downto 0);

  -- Configurações do clock
  signal kp_ck3, kp_ck4: bit;
  constant clockPeriod : time := 10 ns;

    begin
    ck3_tb <= (not ck3_tb) and kp_ck3 after clockPeriod/2;
    ck4_tb <= (not ck4_tb) and kp_ck4 after clockPeriod/2;

    DUT1 : ram
        generic map (
            addressSize => 4,
            wordSize => 8
        )
        port map (
            ck => ck4_tb,
            wr => wr4_tb,
            addr => addr_tb_4bits,
            data_i => datai_tb_4bits,
            data_o => datao_tb_4bits
        );

    stimulus1: process is
    begin
        assert false report "BOT 4bits" severity note;
        kp_ck4 <= '1';

        --teste de escritas
        wr4_tb <= '1';

        addr_tb_4bits <= "0000";
        datai_tb_4bits <= "00000000";
        wait for clockPeriod;
        assert datao_tb_4bits = "00000000" report "Erro na escrita do endereco 0000" severity note;
        wait for clockPeriod;

        addr_tb_4bits <= "0010";
        datai_tb_4bits <= "11000000";
        wait for clockPeriod;
        assert datao_tb_4bits = "11000000" report "Erro na escrita do endereco 0010" severity note;
        wait for clockPeriod;

        addr_tb_4bits <= "0110";
        datai_tb_4bits <= "10101010";
        wait for clockPeriod;
        assert datao_tb_4bits = "10101010" report "Erro na escrita do endereco 0110" severity note;
        wait for clockPeriod;

        addr_tb_4bits <= "1111";
        datai_tb_4bits <= "00001111";
        wait for clockPeriod;
        assert datao_tb_4bits = "00001111" report "Erro na escrita do endereco 1111" severity note;
        wait for clockPeriod;

        addr_tb_4bits <= "1000";
        datai_tb_4bits <= "11100000";
        wait for clockPeriod;
        assert datao_tb_4bits = "11100000" report "Erro na escrita do endereco 1000" severity note;
        wait for clockPeriod;

        --teste de leituras
        wr4_tb <= '0';

        addr_tb_4bits <= "0000";
        wait for 1 ns;
        assert datao_tb_4bits = "00000000" report "Erro na leitura do endereco 0000" severity note;
        wait for 1 ns;

        addr_tb_4bits <= "0010";
        wait for 1 ns;
        assert datao_tb_4bits = "11000000" report "Erro na leitura do endereco 0010" severity note;
        wait for 1 ns;

        addr_tb_4bits <= "0110";
        wait for 1 ns;
        assert datao_tb_4bits = "10101010" report "Erro na leitura do endereco 0110" severity note;
        wait for 1 ns;

        addr_tb_4bits <= "1111";
        wait for 1 ns;
        assert datao_tb_4bits = "00001111" report "Erro na leitura do endereco 1111" severity note;
        wait for 1 ns;

        addr_tb_4bits <= "1000";
        wait for 1 ns;
        assert datao_tb_4bits = "11100000" report "Erro na leitura do endereco 1000" severity note;
        wait for 1 ns;
        
        assert false report "EOT 4bits" severity note;
        kp_ck4 <= '0';

        wait; 
    end process;

    DUT2 : ram
    generic map (
        addressSize => 3,
        wordSize => 4
    )
    port map (
        ck => ck3_tb,
        wr => wr3_tb,
        addr => addr_tb_3bits,
        data_i => datai_tb_3bits,
        data_o => datao_tb_3bits
    );

    stimulus2: process is
        begin
            assert false report "BOT 3bits" severity note;
            kp_ck3 <= '1';

            --teste de escritas
            wr3_tb <= '1';
    
            addr_tb_3bits <= "000";
            datai_tb_3bits <= "0000";
            wait for clockPeriod;
            assert datao_tb_3bits = "0000" report "Erro na escrita do endereco 000" severity note;
            wait for clockPeriod;
    
            addr_tb_3bits <= "010";
            datai_tb_3bits <= "1100";
            wait for clockPeriod;
            assert datao_tb_3bits = "1100" report "Erro na escrita do endereco 010" severity note;
            wait for clockPeriod;
    
            addr_tb_3bits <= "011";
            datai_tb_3bits <= "1010";
            wait for clockPeriod;
            assert datao_tb_3bits = "1010" report "Erro na escrita do endereco 011" severity note;
            wait for clockPeriod;
    
            addr_tb_3bits <= "111";
            datai_tb_3bits <= "1111";
            wait for clockPeriod;
            assert datao_tb_3bits = "1111" report "Erro na escrita do endereco 111" severity note;
            wait for clockPeriod;
    
            addr_tb_3bits <= "100";
            datai_tb_3bits <= "1110";
            wait for clockPeriod;
            assert datao_tb_3bits = "1110" report "Erro na escrita do endereco 100" severity note;
            wait for clockPeriod;
    
            --teste de leituras
            wr3_tb <= '0';
    
            addr_tb_3bits <= "000";
            wait for 1 ns;
            assert datao_tb_3bits = "0000" report "Erro na leitura do endereco 000" severity note;
            wait for 1 ns;
    
            addr_tb_3bits <= "010";
            wait for 1 ns;
            assert datao_tb_3bits = "1100" report "Erro na leitura do endereco 010" severity note;
            wait for 1 ns;
    
            addr_tb_3bits <= "011";
            wait for 1 ns;
            assert datao_tb_3bits = "1010" report "Erro na leitura do endereco 011" severity note;
            wait for 1 ns;
    
            addr_tb_3bits <= "111";
            wait for 1 ns;
            assert datao_tb_3bits = "1111" report "Erro na leitura do endereco 111" severity note;
            wait for 1 ns;
    
            addr_tb_3bits <= "100";
            wait for 1 ns;
            assert datao_tb_3bits = "1110" report "Erro na leitura do endereco 100" severity note;
            wait for 1 ns;
    
            assert false report "EOT 3bits" severity note;
            kp_ck3 <= '0';

        wait; 
    end process;
end architecture;

Memórias/RAM/teste.vcd
$date
  Tue Sep 29 10:44:40 2020
$end
$version
  GHDL v0
$end
$timescale
  1 fs
$end
$scope module standard $end
$upscope $end
$scope module std_logic_1164 $end
$upscope $end
$scope module numeric_std $end
$upscope $end
$scope module ram_tb $end
$var reg 1 ! ck3_tb $end
$var reg 1 " ck4_tb $end
$var reg 1 # wr3_tb $end
$var reg 1 $ wr4_tb $end
$var reg 4 % addr_tb_4bits[3:0] $end
$var reg 8 & datai_tb_4bits[7:0] $end
$var reg 8 ' datao_tb_4bits[7:0] $end
$var reg 3 ( addr_tb_3bits[2:0] $end
$var reg 4 ) datai_tb_3bits[3:0] $end
$var reg 4 * datao_tb_3bits[3:0] $end
$var reg 1 + kp_ck3 $end
$var reg 1 , kp_ck4 $end
$scope module dut1 $end
$var reg 1 - ck $end
$var reg 1 . wr $end
$var reg 4 / addr[3:0] $end
$var reg 8 0 data_i[7:0] $end
$var reg 8 1 data_o[7:0] $end
$comment mem is not handled $end
$upscope $end
$scope module dut2 $end
$var reg 1 2 ck $end
$var reg 1 3 wr $end
$var reg 3 4 addr[2:0] $end
$var reg 4 5 data_i[3:0] $end
$var reg 4 6 data_o[3:0] $end
$comment mem is not handled $end
$upscope $end
$upscope $end
$enddefinitions $end
#0
0!
0"
1#
1$
b0000 %
b00000000 &
b00000000 '
b000 (
b0000 )
b0000 *
1+
1,
0-
1.
b0000 /
b00000000 0
b00000000 1
02
13
b000 4
b0000 5
b0000 6
#5000000
1!
1"
1-
12
#10000000
0!
0"
0-
02
#15000000
1!
1"
1-
12
#20000000
0!
0"
b0010 %
b11000000 &
b010 (
b1100 )
0-
b0010 /
b11000000 0
02
b010 4
b1100 5
#25000000
1!
1"
b11000000 '
b1100 *
1-
b11000000 1
12
b1100 6
#30000000
0!
0"
0-
02
#35000000
1!
1"
1-
12
#40000000
0!
0"
b0110 %
b10101010 &
b00000000 '
b011 (
b1010 )
b0000 *
0-
b0110 /
b10101010 0
b00000000 1
02
b011 4
b1010 5
b0000 6
#45000000
1!
1"
b10101010 '
b1010 *
1-
b10101010 1
12
b1010 6
#50000000
0!
0"
0-
02
#55000000
1!
1"
1-
12
#60000000
0!
0"
b1111 %
b00001111 &
b00000000 '
b111 (
b1111 )
b0000 *
0-
b1111 /
b00001111 0
b00000000 1
02
b111 4
b1111 5
b0000 6
#65000000
1!
1"
b00001111 '
b1111 *
1-
b00001111 1
12
b1111 6
#70000000
0!
0"
0-
02
#75000000
1!
1"
1-
12
#80000000
0!
0"
b1000 %
b11100000 &
b00000000 '
b100 (
b1110 )
b0000 *
0-
b1000 /
b11100000 0
b00000000 1
02
b100 4
b1110 5
b0000 6
#85000000
1!
1"
b11100000 '
b1110 *
1-
b11100000 1
12
b1110 6
#90000000
0!
0"
0-
02
#95000000
1!
1"
1-
12
#100000000
0!
0"
0#
0$
b0000 %
b00000000 '
b000 (
b0000 *
0-
0.
b0000 /
b00000000 1
02
03
b000 4
b0000 6
#101000000
#102000000
b0010 %
b11000000 '
b010 (
b1100 *
b0010 /
b11000000 1
b010 4
b1100 6
#103000000
#104000000
b0110 %
b10101010 '
b011 (
b1010 *
b0110 /
b10101010 1
b011 4
b1010 6
#105000000
1!
1"
1-
12
#106000000
b1111 %
b00001111 '
b111 (
b1111 *
b1111 /
b00001111 1
b111 4
b1111 6
#107000000
#108000000
b1000 %
b11100000 '
b100 (
b1110 *
b1000 /
b11100000 1
b100 4
b1110 6
#109000000
#110000000
0!
0"
0+
0,
0-
02
